LICENSE
MANIFEST.in
README.rst
setup.py
line/__init__.py
line/api.py
line/client.py
line/models.py
line.egg-info/PKG-INFO
line.egg-info/SOURCES.txt
line.egg-info/dependency_links.txt
line.egg-info/pbr.json
line.egg-info/requires.txt
line.egg-info/top_level.txt